fumetest_cli/__init__.py
fumetest_cli/fumetest_cli.py
fumetest_cli-0.1.1.dist-info/METADATA
fumetest_cli-0.1.1.dist-info/WHEEL
fumetest_cli-0.1.1.dist-info/entry_points.txt
fumetest_cli-0.1.1.dist-info/top_level.txt
fumetest_cli-0.1.1.dist-info/RECORD
