Metadata-Version: 2.1
Name: fumetest-cli
Version: 0.1.1
Summary: UNKNOWN
Home-page: UNKNOWN
Author: UNKNOWN
Author-email: UNKNOWN
License: UNKNOWN
Platform: UNKNOWN
Requires-Dist: click
Requires-Dist: selenium
Requires-Dist: python-dateutil
